.gitignore
COPYING
LICENSE
Makefile
Pathomx.py
README.md
developer_install_linux.sh
developer_install_linux_python3.sh
developer_install_mac.sh
do_metacyc_import.py
init_database.py
install_name_fix.sh
release_debian.sh
release_mac.sh
release_windows.bat
requirements.txt
setup.installers.py
setup.mac.py
setup.py
stdeb.cfg
Pathomx.egg-info/PKG-INFO
Pathomx.egg-info/SOURCES.txt
Pathomx.egg-info/dependency_links.txt
Pathomx.egg-info/entry_points.txt
Pathomx.egg-info/requires.txt
Pathomx.egg-info/top_level.txt
docs/Makefile
docs/Pathomx.rst
docs/api.rst
docs/conf.py
docs/custom_exceptions.rst
docs/data.rst
docs/dev_install.rst
docs/index.rst
docs/install.rst
docs/make.bat
docs/plugins.rst
docs/translate.rst
docs/ui.rst
docs/views.rst
docs/images/pathomx-v2-visual-editor.png
pathomx/Pathomx.py
pathomx/__init__.py
pathomx/cleanup.sh
pathomx/custom_exceptions.py
pathomx/data.py
pathomx/db.py
pathomx/displayobjects.py
pathomx/figures.py
pathomx/globals.py
pathomx/kernel_helpers.py
pathomx/pep8ify-all
pathomx/plugins.py
pathomx/qt.py
pathomx/runqueue.py
pathomx/tools.py
pathomx/translate.py
pathomx/ui.py
pathomx/utils.py
pathomx/views.py
pathomx/xref.py
pathomx/xref_fix.py
pathomx/database/CdeltaGkegg.csv
pathomx/database/CdeltaGlit.csv
pathomx/database/RdeltaGkegg.csv
pathomx/database/compounds
pathomx/database/genes
pathomx/database/gibbs
pathomx/database/gibbs-r
pathomx/database/pathways
pathomx/database/proteins
pathomx/database/reactions
pathomx/database/synonyms
pathomx/database/figures/10-FORMYL-THF.png
pathomx/database/figures/2-3-CARBOXY-3-AMINOPROPYL-L-HISTIDINE.png
pathomx/database/figures/2-3-CARBOXY-3-METHYLAMMONIOPROPYL-L-.png
pathomx/database/figures/2-AMINO-3-3-OXOPROP-2-ENYL-BUT-2-ENEDI.png
pathomx/database/figures/2-AMINO-MUCONATE.png
pathomx/database/figures/2-AMINOMUCONATE_SEMIALDEHYDE.png
pathomx/database/figures/2-HYDROXY-3-KETO-5-METHYLTHIO-1-PHOSPHOP.png
pathomx/database/figures/2-KETO-3-METHYL-VALERATE.png
pathomx/database/figures/2-KETO-ISOVALERATE.png
pathomx/database/figures/2-KETOGLUTARATE.png
pathomx/database/figures/2-METHYL-3-HYDROXY-BUTYRYL-COA.png
pathomx/database/figures/2-METHYL-ACETO-ACETYL-COA.png
