Metadata-Version: 1.1
Name: Pathomx
Version: 3.0.2
Summary: Metabolic pathway visualisation and analysis.
Home-page: https://github.com/pathomx/pathomx
Author: Martin Fitzpatrick
Author-email: martin.fitzpatrick@gmail.com
License: GPL
Download-URL: https://github.com/pathomx/pathomx/zipball/master
Keywords: bioinformatics data analysis metabolomics research science
Platform: UNKNOWN
Classifier: Development Status :: 3 - Alpha
Classifier: Natural Language :: English
Classifier: Operating System :: OS Independent
Classifier: Programming Language :: Python :: 2
Classifier: License :: OSI Approved :: GNU General Public License v3 (GPLv3)
Classifier: Topic :: Scientific/Engineering :: Bio-Informatics
Classifier: Topic :: Education
Classifier: Intended Audience :: Science/Research
Classifier: Intended Audience :: Education
